[
{"item_name":"Итальянская import","small_size_price":19,"description":"Томатный соус, пикантная пепперони, маслины, шампиньоны, моцарелла, итальянские травы","item_image":"\\images\\1699538454175-italian.webp"}
,
{"item_name":"Четыре сыра import","small_size_price":21,"description":"Увеличенная порция моцареллы, сыры чеддер и пармезан, сыр блю чиз, соус альфредо","item_image":"\\images\\1699538476852-4_cheeses.webp"}
,
{"item_name":"Четыре сезона import","small_size_price":19,"description":"Томатный соус, пикантная пепперони, ветчина, кубики брынзы, томаты, шампиньоны, моцарелла, итальянские травы","item_image":"\\images\\1699538505064-4_seasons.webp"}
]